{"data":[
	[
		{"sectiontitle":"Assessment 1 Resources",
		"sectiondata":[
			{"title":"Architecture Document", "icon":"description","date":"Updated 8 Nov 2017, 10:21 GMT", "link":"/content/Arch1.pdf"},
			{"title":"Method selection and planning document", "icon":"description","date":"Added 7 Nov 2017, 14:40 GMT", "link":"/content/Plan1.pdf"},
			{"title":"Requirements document", "icon":"description","date":"Updated 8 Nov 2017, 10:21 GMT", "link":"/content/Req1.pdf"},
			{"title":"Risk assessment and mitigation document", "icon":"description","date":"Added 7 Nov 2017, 14:40 GMT", "link":"/content/Risk1.pdf"}
		]},
		{"sectiontitle":"Assessment 1 Extras",
		"sectiondata":[
			{"title":"Gantt Charts", "icon":"timeline","date":"First line", "link":"https://docs.google.com/a/york.ac.uk/spreadsheets/d/11NNjvenq0gTta2dcQxxmluznd9xA3Oe9EsYfJGzJJSA/edit?usp=sharing"},
			{"title":"Use case document", "icon":"description","date":"First Line", "link":"/content/Usecase1.pdf"},
			{"title":"Image of paper prototype", "icon":"photo","date":"First Line", "link":"/content/Prototype1.png"}
		]}
		
	],[
		{"sectiontitle":"Assessment 2 Resources",
		"sectiondata":[
			{"title":"Architecture report", "icon":"description","date":"Added 22 Jan 2018, 03:11 GMT", "link":"/content/Arch2.pdf"},
			{"title":"Implementation report", "icon":"description","date":"Added 21 Jan 2018, 23:39 GMT", "link":"/content/Impl2.pdf"},
			{"title":"Executable", "icon":"games","date":"Released 22 Jan 2018, 00:37 GMT", "link":"https://github.com/SEPR-Team-Margaret/UniversityDomination/releases/tag/v.1.0"},
			{"title":"Graphical User Interface report", "icon":"description","date":"Added 21 Jan 2018, 23:39 GMT", "link":"/content/GUI2.pdf"},
			{"title":"Testing report", "icon":"description","date":"Updated 22 Jan 2018, 00:18 GMT", "link":"/content/Test2.pdf"},
			{"title":"Update listing", "icon":"description","date":"Updated 22 Jan 2018, 14:09 GMT", "link":"/content/Updates2.pdf"}
		]},
		{"sectiontitle":"Updated Assessment 1 Deliverables",
		"sectiondata":[
			{"title":"Requirements document", "icon":"description","date":"Added 21 Jan 2018, 23:11 GMT", "link":"/content/Req1U2.pdf"},
			{"title":"Method selection and planning document", "icon":"description","date":"Added 21 Jan 2018, 23:11 GMT", "link":"/content/Plan1U2.pdf"},
			{"title":"Risk assessment and mitigation document", "icon":"description","date":"Added 21 Jan 2018, 23:11 GMT", "link":"/content/Risk1U2.pdf"},
			{"title":"Updated Gantt Chart", "icon":"timeline","date":"Updated 22 Jan 2018, 14:03 GMT [Link updated, check content for version history]", "link":"https://docs.google.com/a/york.ac.uk/spreadsheets/d/1pdrsGgI43a44hy373MQwDyupTc0J5IFbdG-vdIrdpNg/edit?usp=sharing"}
		]},
		{"sectiontitle":"Assessment 2 Extras",
		"sectiondata":[
			{"title":"Updated abstract architecture (Limited scope)", "icon":"photo","date":"Added 22 Jan 2018, 00:46 GMT", "link":"content/OOScope1U2.png"},
			{"title":"Unit test results", "icon":"description","date":"Added 21 Jan 2018, 23:33 GMT", "link":"/content/UnitT2.pdf"},
			{"title":"GUI testing document", "icon":"description","date":"Updated 22 Jan 2018, 00:20 GMT", "link":"/content/GUIT2.pdf"},
			{"title":"GUI test results", "icon":"description","date":"Added 21 Jan 2018, 23:58 GMT", "link":"/content/GUITR2.pdf"},
			{"title":"Test design document", "icon":"description","date":"Added 21 Jan 2018, 23:33 GMT", "link":"/content/TestD2.pdf"},
			{"title":"Unit Tests", "icon":"perm_media","date":"Added 21 Jan 2018, 23:44 GMT", "link":"/content/UnitTests2.zip"},
			{"title":"Player Turn Sequence Diagram", "icon":"photo","date":"Added 22 Jan 2018, 00:51 GMT", "link":"/content/PTDiag2.png"},
			{"title":"Updated Architecture Document", "icon":"description","date":"Added 22 Jan 2018, 01:04 GMT", "link":"/content/Arch1U2.pdf"},
			{"title":"UML Concrete Architecture Diagram", "icon":"photo","date":"Added 22 Jan 2018, 02:23 GMT", "link":"/content/UMLC2.png"},
			{"title":"User Manual", "icon":"description","date":"Added 22 Jan 2018, 09:32 GMT", "link":"/content/UM2.pdf"},
			{"title":"User Manual (Source)", "icon":"description","date":"Updated 22 Jan 2018, 09:32 GMT [Link updated, check content for version history]", "link":"https://docs.google.com/a/york.ac.uk/document/d/1VFXTba_ZufPQBi4Pcp4HEdnH2otyL0B8ox3AqczqXbU/edit?usp=sharing"}
		]}
	],[
		{"sectiontitle":"Assessment 3 Resources",
		"sectiondata":[
			{"title":"Change report", "icon":"description","date":"Added 19 Feb 2018, 01:36 GMT", "link":"/content/Chan3.pdf"},
			{"title":"Implementation report", "icon":"description","date":"Updated 19 Feb 2018, 11:48 GMT", "link":"/content/Impl3.pdf"},
			{"title":"Executable Download", "icon":"games","date":"Updated 19 Feb 2018 11:52 GMT", "link":"/content/Build03.zip"},
			{"title":"GUI Report", "icon":"description","date":"Added 18 Feb 2018, 23:51 GMT", "link":"/content/GUI3.pdf"},
			{"title":"Methods Document", "icon":"description","date":"Added 19 Feb 2018, 01:42 GMT", "link":"/content/Meth3.pdf"},
			{"title":"Testing Report", "icon":"description","date":"Updated 19 Feb 2018, 11:25 GMT", "link":"/content/Test3.pdf"},
			{"title":"Risk Assessment", "icon":"description","date":"Added 18 Feb 2018, 23:51 GMT", "link":"/content/Risk3.pdf"},
			{"title":"User Manual", "icon":"description","date":"Added 19 Feb 2018, 11:38 GMT", "link":"/content/User3.pdf"}
		]},
		{"sectiontitle":"Assessment 3 Extras",
		"sectiondata":[
			{"title":"Debug Tests Spreadsheet", "icon":"description","date":"Added 19 Feb 2018, 01:49 GMT", "link":"https://docs.google.com/spreadsheets/d/1PXLIjwJtNB-7d3w3rADbcvFgGOfSD286wwnDMj3Ib7k/edit?usp=sharing"},
			{"title":"Tracibility Spreadsheet", "icon":"description","date":"Added 19 Feb 2018, 01:49 GMT", "link":"https://docs.google.com/spreadsheets/d/1y8bav7AK3Zen4NJuNlf_A-K6hLMazjyxcAfqppaMoW0/edit?usp=sharing"},
			{"title":"Test Results", "icon":"description","date":"Added 19 Feb 2018, 10:23 GMT", "link":"/content/TestM3.pdf"},
			{"title":"Testing Outline", "icon":"description","date":"Added 19 Feb 2018, 00:01 GMT", "link":"/content/TestO3.pdf"},
			{"title":"Original Group's Website", "icon":"insert_link","date":"Added 19 Feb 2018, 00:04 GMT [3rd Party Site; reliablity not assured]", "link":"http://risk-assessment.my-free.website/"},
			{"title":"User Manual Source", "icon":"description","date":"Updated 18 Feb 2018, 23:57 GMT [Link updated, check content for version history]", "link":"https://docs.google.com/document/d/187j4dOEtA9fz2VKJk6g35fn3R3CqCU7qC9SebunoDFE/edit?usp=sharing"}
		]}
	
	],
	[
		{"sectiontitle":"Assessment 4 Resources",
			"sectiondata":[
				{"title":"Final Architecture and Traceability Report", "icon":"description","date":"Unavailable", "link":"#"},
				{"title":"Implementation report", "icon":"description","date":"Unavailable", "link":"#"},
				{"title":"Evaluation and Testing report", "icon":"description","date":"Unavailable", "link":"#"},
				{"title":"Project Review Report", "icon":"description","date":"Updated 1 May 2018, 22:31 GMT", "link":"/content/Review4.pdf"},
				{"title":"Executable Download", "icon":"games","date":"Added 1 May 2018, 22:15 GMT", "link":"/content/Build04.pdf"},
				{"title":"Source Code", "icon":"games","date":"Github VCS Repository", "link":"https://github.com/SEPR-Team-Margaret/ud-asm4"}
			]},
			{"sectiontitle":"Assessment 4 Extras",
			"sectiondata":[
				{"title":"Traceability Spreadsheet", "icon":"timeline","date":"Updated 01 May 2018, 17:44 GMT [Link updated, check content for version history]", "link":"https://docs.google.com/spreadsheets/d/1s0Fh1ty4dXZ7Vb2xIcwNgl3QX22hb57tFK5fKbyUCyA/edit?usp=sharing"},
				{"title":"Unit Test Results", "icon":"description","date":"Added 1 May 2018, 21:54 GMT", "link":"/content/UnitT4.pdf"},
				{"title":"Updated Requirements documentation", "icon":"description","date":"Added 1 May 2018, 22:07 GMT", "link":"/content/Req4.pdf"},
				{"title":"Architecture Diagram", "icon":"photo","date":"Added 1 May 2018, 22:7 GMT", "link":"/content/ArchD4.svg"}
		]}
	]
]}